mecord/__init__.py
mecord/constant.py
mecord/main.py
mecord/mecord_server_socket.py
mecord/mecord_service.py
mecord/mecord_widget.py
mecord/progress_monitor.py
mecord/server_func.py
mecord/shared_memory.py
mecord/store.py
mecord/task.py
mecord/taskUtils.py
mecord/upload.py
mecord/utils.py
mecord/xy_network.py
mecord/xy_pb.py
mecord/pb/__init__.py
mecord/pb/aigc_ext_pb2.py
mecord/pb/aigc_int_pb2.py
mecord/pb/cmd_id_ext_pb2.py
mecord/pb/common_ext_pb2.py
mecord/pb/interaction_int_pb2.py
mecord/pb/mecord_ext_pb2.py
mecord/pb/message_ext_pb2.py
mecord/pb/rpcinput_pb2.py
mecord/pb/search_ext_pb2.py
mecord/pb/studio_ext_pb2.py
mecord/pb/tarsproxy_pb2.py
mecord/pb/uauth_common_pb2.py
mecord/pb/uauth_ext_pb2.py
mecord/pb/user_ext_pb2.py
mecord/pb/user_status_ext_pb2.py
mecord/script_template/__init__.py
mecord/script_template/launch.py
mecord/script_template/main.py
mecord/script_template/run.py
mecord/widget_template/MekongJS.js.py
mecord/widget_template/__init__.py
mecord/widget_template/config.json.py
mecord/widget_template/icon.png.py
mecord/widget_template/index.html.py
mecord_cli-0.7.411.dist-info/LICENSE
mecord_cli-0.7.411.dist-info/METADATA
mecord_cli-0.7.411.dist-info/WHEEL
mecord_cli-0.7.411.dist-info/entry_points.txt
mecord_cli-0.7.411.dist-info/top_level.txt
mecord_cli-0.7.411.dist-info/RECORD
