Metadata-Version: 2.1
Name: mecord-cli
Version: 0.7.411
Summary: mecord tools
Home-page: https://github.com/mecordofficial
Author: pengjun
Author-email: mr_lonely@foxmail.com
Classifier: Programming Language :: Python :: 3
Classifier: License :: OSI Approved :: MIT License
Classifier: Operating System :: OS Independent
Requires-Python: >=3.4
License-File: LICENSE
Requires-Dist: requests
Requires-Dist: uuid
Requires-Dist: Image
Requires-Dist: pillow
Requires-Dist: protobuf
Requires-Dist: oss2
Requires-Dist: psutil
Requires-Dist: pynvml
Requires-Dist: requests-toolbelt
Requires-Dist: matplotlib
Requires-Dist: ping3
Requires-Dist: piexif
Requires-Dist: gputil
Requires-Dist: urlparser
Requires-Dist: setuptools
Requires-Dist: twine
Requires-Dist: uvicorn >=0.21.1
Requires-Dist: fastapi >=0.94.0
Requires-Dist: python-crontab
Requires-Dist: websocket-client >=1.7.0
